livekit_tools/__init__.py
livekit_tools/__main__.py
livekit_tools/livekit_frames.py
livekit_tools/livekit_token.py
livekit_tools/livekit_url.py
livekit_tools/py.typed
livekit_tools-0.0.0.dev2.dist-info/LICENSE
livekit_tools-0.0.0.dev2.dist-info/METADATA
livekit_tools-0.0.0.dev2.dist-info/WHEEL
livekit_tools-0.0.0.dev2.dist-info/entry_points.txt
livekit_tools-0.0.0.dev2.dist-info/top_level.txt
livekit_tools-0.0.0.dev2.dist-info/zip-safe
livekit_tools-0.0.0.dev2.dist-info/RECORD
