Metadata-Version: 2.1
Name: livekit-tools
Version: 0.0.0.dev2
Summary: livekit common utilities
Author-email: David Guerizec <david@guerizec.net>
License: Apache License
Project-URL: github, https://github.com/dguerizec/livekit_tools
Keywords: livekit,camera,capture,console,token
Platform: Linux
Classifier: Development Status :: 4 - Beta
Classifier: Intended Audience :: Developers
Classifier: License :: Other/Proprietary License
Classifier: Operating System :: POSIX :: Linux
Classifier: Programming Language :: Python
Classifier: Programming Language :: Python :: 3
Classifier: Programming Language :: Python :: 3 :: Only
Classifier: Programming Language :: Python :: 3.10
Requires-Python: >=3.10
License-File: LICENSE
Requires-Dist: PyJWT
Requires-Dist: numpy
Requires-Dist: livekit
Requires-Dist: livekit-api
Requires-Dist: pytimeparse2
Requires-Dist: typer
Provides-Extra: dev
Requires-Dist: ipdb ; extra == 'dev'
Requires-Dist: ipython <8.2.0 ; extra == 'dev'
Requires-Dist: mypy ; extra == 'dev'
Requires-Dist: mypy-extensions ; extra == 'dev'
Requires-Dist: typing-extensions ; extra == 'dev'
Requires-Dist: types-setuptools ; extra == 'dev'
Provides-Extra: lint
Requires-Dist: black ; extra == 'lint'
Requires-Dist: isort ; extra == 'lint'
Requires-Dist: ruff ; extra == 'lint'
Requires-Dist: flake8 ; extra == 'lint'
Requires-Dist: flake8-bugbear ; extra == 'lint'
Requires-Dist: flake8-comprehensions ; extra == 'lint'
Requires-Dist: flake8-docstrings ; extra == 'lint'
Requires-Dist: flake8-formatter-abspath ; extra == 'lint'
Requires-Dist: pycodestyle ; extra == 'lint'
Requires-Dist: pydocstyle ; extra == 'lint'
Requires-Dist: pylint ; extra == 'lint'
Requires-Dist: reformat-gherkin ; extra == 'lint'
Provides-Extra: tests
Requires-Dist: mock ; extra == 'tests'
Requires-Dist: pytest ; extra == 'tests'
Requires-Dist: pytest-asyncio ; extra == 'tests'
Requires-Dist: coverage-conditional-plugin ; extra == 'tests'
Requires-Dist: pytest-bdd ; extra == 'tests'
Requires-Dist: pytest-cov ; extra == 'tests'
Requires-Dist: pytest-lazy-fixture ; extra == 'tests'
Requires-Dist: pytest-sugar ; extra == 'tests'
Requires-Dist: types-mock ; extra == 'tests'
